cdk_cloudformation_spot_elastigroup_group/__init__.py
cdk_cloudformation_spot_elastigroup_group/py.typed
cdk_cloudformation_spot_elastigroup_group/_jsii/__init__.py
cdk_cloudformation_spot_elastigroup_group/_jsii/spot-elastigroup-group@1.0.5-alpha.7.jsii.tgz
cdk_cloudformation_spot_elastigroup_group-1.0.5a7.dist-info/LICENSE
cdk_cloudformation_spot_elastigroup_group-1.0.5a7.dist-info/METADATA
cdk_cloudformation_spot_elastigroup_group-1.0.5a7.dist-info/WHEEL
cdk_cloudformation_spot_elastigroup_group-1.0.5a7.dist-info/top_level.txt
cdk_cloudformation_spot_elastigroup_group-1.0.5a7.dist-info/RECORD
